odoo/addons/pos_partner_firstname/README.rst
odoo/addons/pos_partner_firstname/__init__.py
odoo/addons/pos_partner_firstname/__manifest__.py
odoo/addons/pos_partner_firstname/i18n/ca.po
odoo/addons/pos_partner_firstname/i18n/ca_ES.po
odoo/addons/pos_partner_firstname/i18n/de.po
odoo/addons/pos_partner_firstname/i18n/es.po
odoo/addons/pos_partner_firstname/i18n/fr.po
odoo/addons/pos_partner_firstname/i18n/fr_CH.po
odoo/addons/pos_partner_firstname/i18n/it.po
odoo/addons/pos_partner_firstname/i18n/pos_partner_firstname.pot
odoo/addons/pos_partner_firstname/models/__init__.py
odoo/addons/pos_partner_firstname/models/pos_config.py
odoo/addons/pos_partner_firstname/models/pos_session.py
odoo/addons/pos_partner_firstname/readme/CONTRIBUTORS.md
odoo/addons/pos_partner_firstname/readme/DESCRIPTION.md
odoo/addons/pos_partner_firstname/readme/ROADMAP.md
odoo/addons/pos_partner_firstname/static/description/icon.png
odoo/addons/pos_partner_firstname/static/description/index.html
odoo/addons/pos_partner_firstname/static/src/app/PartnerDetailsEdit.esm.js
odoo/addons/pos_partner_firstname/static/src/app/PartnerDetailsEdit.scss
odoo/addons/pos_partner_firstname/static/src/app/PartnerDetailsEdit.xml
odoo_addon_pos_partner_firstname-17.0.1.0.1.2.dist-info/METADATA
odoo_addon_pos_partner_firstname-17.0.1.0.1.2.dist-info/WHEEL
odoo_addon_pos_partner_firstname-17.0.1.0.1.2.dist-info/top_level.txt
odoo_addon_pos_partner_firstname-17.0.1.0.1.2.dist-info/RECORD
